gpam-ml-lib/__init__.py
gpam-ml-lib/loss_funct.py
gpam-ml-lib/networks.py
gpam-ml-lib/utils.py
gpam_ml_lib/__init__.py
gpam_ml_lib/loss_funct.py
gpam_ml_lib/networks.py
gpam_ml_lib/preprocessing.py
gpam_ml_lib/utils.py
gpam_ml_lib-0.0.2.1.dist-info/METADATA
gpam_ml_lib-0.0.2.1.dist-info/WHEEL
gpam_ml_lib-0.0.2.1.dist-info/top_level.txt
gpam_ml_lib-0.0.2.1.dist-info/RECORD
